calculate/__init__.py
calculate/fps.py
calfps-0.0.7.dist-info/LICENSE.txt
calfps-0.0.7.dist-info/METADATA
calfps-0.0.7.dist-info/WHEEL
calfps-0.0.7.dist-info/top_level.txt
calfps-0.0.7.dist-info/RECORD
